base/__init__.py
base/base.py
algo_base-0.0.3.dist-info/METADATA
algo_base-0.0.3.dist-info/WHEEL
algo_base-0.0.3.dist-info/top_level.txt
algo_base-0.0.3.dist-info/zip-safe
algo_base-0.0.3.dist-info/RECORD
