Metadata-Version: 2.1
Name: algo-base
Version: 0.0.3
Summary: 组件开发基础工具
Home-page: https://www.baidu.com
Author: Contributors
Author-email: mli@amazon.com
License: Apache-2.0
Platform: all
